starriver-0.0.0.dist-info/METADATA
starriver-0.0.0.dist-info/WHEEL
starriver-0.0.0.dist-info/entry_points.txt
starriver/__init__.py
starriver-0.0.0.dist-info/RECORD
